matrix.cpython-39-darwin.so
egrm/__init__.py
egrm/egrm.py
egrm-0.1.data/scripts/trees2egrm
egrm-0.1.dist-info/LICENSE
egrm-0.1.dist-info/METADATA
egrm-0.1.dist-info/WHEEL
egrm-0.1.dist-info/top_level.txt
egrm-0.1.dist-info/RECORD
