Metadata-Version: 2.1
Name: egrm
Version: 0.1
Summary: Expected Genetic Relationship Matrix
Home-page: https://github.com/Ephraim-usc/egrm.git
Author: Caoqi Fan
Author-email: caoqifan@usc.edu
License: UNKNOWN
Keywords: genetics genome SNP coalescence
Platform: UNKNOWN
Classifier: Programming Language :: Python :: 3.7
Classifier: License :: OSI Approved :: MIT License
Classifier: Topic :: Scientific/Engineering :: Bio-Informatics
Requires-Python: >=3
License-File: LICENSE
Requires-Dist: numpy (>=1.14.5)
Requires-Dist: pandas (>=1.2.0)
Requires-Dist: tskit
Requires-Dist: tqdm
